moimage/__init__.py
moimage/image_clipboard_widget.py
moimage/image_download_widget.py
moimage/image_outline_widget.py
moimage/image_upload_widget.py
moimage/image_widget.py
moimage/static/js/image_clipboard_widget.js
moimage/static/js/image_download_widget.js
moimage/static/js/image_outline_widget.js
moimage/static/js/image_upload_widget.js
moimage/static/js/image_widget.js
moimage-0.1.0.data/data/moimage/static/js/image_clipboard_widget.js
moimage-0.1.0.data/data/moimage/static/js/image_download_widget.js
moimage-0.1.0.data/data/moimage/static/js/image_outline_widget.js
moimage-0.1.0.data/data/moimage/static/js/image_upload_widget.js
moimage-0.1.0.data/data/moimage/static/js/image_widget.js
moimage-0.1.0.dist-info/METADATA
moimage-0.1.0.dist-info/WHEEL
moimage-0.1.0.dist-info/RECORD
