Metadata-Version: 2.4
Name: moimage
Version: 0.1.0
Summary: A modern image widget for Jupyter notebooks and Python environments
Project-URL: Homepage, https://github.com/yourusername/moimage
Project-URL: Repository, https://github.com/yourusername/moimage
Project-URL: Issues, https://github.com/yourusername/moimage/issues
Author-email: Your Name <your.email@example.com>
License: MIT
Classifier: Development Status :: 3 - Alpha
Classifier: Framework :: Jupyter
Classifier: Framework :: Jupyter :: JupyterLab
Classifier: Framework :: Jupyter :: JupyterLab :: 3
Classifier: Framework :: Jupyter :: JupyterLab :: 4
Classifier: Intended Audience :: Developers
Classifier: License :: OSI Approved :: MIT License
Classifier: Programming Language :: Python :: 3
Classifier: Programming Language :: Python :: 3.8
Classifier: Programming Language :: Python :: 3.9
Classifier: Programming Language :: Python :: 3.10
Classifier: Programming Language :: Python :: 3.11
Classifier: Programming Language :: Python :: 3.12
Requires-Python: >=3.8
Requires-Dist: anywidget>=0.9.0
Requires-Dist: pillow>=8.0.0
Requires-Dist: traitlets>=5.0.0
Provides-Extra: dev
Requires-Dist: black; extra == 'dev'
Requires-Dist: jupyter; extra == 'dev'
Requires-Dist: jupyterlab; extra == 'dev'
Requires-Dist: pytest; extra == 'dev'
Requires-Dist: pytest-cov; extra == 'dev'
Requires-Dist: ruff; extra == 'dev'
